{
  "observations": {
    "items": {
      "resourceName": {
        "ui:placeholder": "Enter the name of the resource"
      },
      "observationType": {
        "ui:widget": "select",
        "ui:placeholder": "Select an observation type"
      },
      "details": {
        "ui:widget": "textarea",
        "ui:placeholder": "Enter details of the observation",
        "ui:options": {
          "rows": 5
        }
      },
      "referencePublication": {
        "ui:placeholder": "Enter publication DOI"
      },
      "fileUpload": {
        "ui:widget": "file"
      }
    },
    "ui:options": {
      "addButtonText": "Add Observation"
    }
  }
}
