{
  "_source": "mining",
  "_publications": [
    {
      "_pmid": "PMID:35118381",
      "_doi": "10.1093/noajnl/vdab184",
      "_publicationTitle": "Neutrophil depletion enhanced the "
    }
  ],
  "_confidence": "0.9",
  "_foundIn": "Results",
  "_contextSnippet": "Tumors were harvested 24 hours after the spore injection and staining via H&E and Gram demonstrated extensive germination, accompanied by marked accumulation of polymorphonuclear granulocytes",
  "resourceType": "Cell Line",
  "resourceName": "GL261",
  "observationType": "Other",
  "details": "Tumors showed extensive germination accompanied by marked accumulation of polymorphonuclear granulocytes located between germinating bacteria and remaining viable tumor, mainly around the outer rim area",
  "referencePublication": "10.1093/noajnl/vdab184"
}