{
  "_source": "mining",
  "_publications": [
    {
      "_pmid": "PMID:34930951",
      "_doi": "10.1038/s41536-021-00195-3",
      "_publicationTitle": "A bioinspired gelatin-hyaluronic acid-based hybrid interpenetrating network for the enhancement of retinal ganglion cells replacement therapy."
    }
  ],
  "_confidence": "0.95",
  "_foundIn": "Results",
  "_contextSnippet": "Of the initial 5 × 10⁴ injected cells, the following are the percentages of the viable engrafted cells found 1 month after injection: 52% for Gtn-HPA; 53% for IPN75; 56% for IPN50; and 38% for PBS.",
  "resourceType": "Cell Line",
  "resourceName": "human retinal ganglion cells (hRGC)",
  "observationType": "Other",
  "details": "Engraftment percentages after 1 month: 52% for Gtn-HPA, 53% for IPN75, 56% for IPN50, and 38% for PBS from initial 5×10⁴ injected cells",
  "referencePublication": "10.1038/s41536-021-00195-3"
}