{
  "_source": "mining",
  "_publications": [
    {
      "_pmid": "PMID:39620202",
      "_doi": "10.1093/noajnl/vdae188",
      "_publicationTitle": "Multiomic analyses reveal new targets of polycomb repressor complex 2 in Schwann lineage cells and malignant peripheral nerve sheath tumors."
    }
  ],
  "_confidence": "0.95",
  "_foundIn": "Results",
  "_contextSnippet": "Most genes whose expression changed after the loss of SUZ12 or EED on an NF1-deficient background, 81% and 87%, respectively, were upregulated",
  "resourceType": "Cell Line",
  "resourceName": "iHSCs",
  "observationType": "Other",
  "details": "81% and 87% of genes were upregulated after loss of SUZ12 or EED respectively on an NF1-deficient background",
  "referencePublication": "10.1093/noajnl/vdae188"
}