{
  "_source": "mining",
  "_publications": [
    {
      "_pmid": "PMID:35511749",
      "_doi": "10.1158/1535-7163.MCT-21-0947",
      "_publicationTitle": "A High-Throughput Screening Platform Identifies Novel Combination Treatments for Malignant Peripheral Nerve Sheath Tumors."
    }
  ],
  "_confidence": "0.95",
  "_foundIn": "Results",
  "_contextSnippet": "from the eighteen combinations that met this criterion for the MPNST-SP-01 cell line, seven included Panobinostat (histone deacetylase inhibitor) combined with compounds targeting many different targets",
  "resourceType": "Cell Line",
  "resourceName": "MPNST-SP-01",
  "observationType": "Other",
  "details": "18 combinations met DBSumNeg values lower than -7, with 7 including Panobinostat",
  "referencePublication": "10.1158/1535-7163.MCT-21-0947"
}