{
  "_source": "mining",
  "_publications": [
    {
      "_pmid": "PMID:33658640",
      "_doi": "10.1038/s41416-021-01270-8",
      "_publicationTitle": "Exploring transcriptional regulators Ref-1 and STAT3 as therapeutic targets in malignant peripheral nerve sheath tumours."
    }
  ],
  "_confidence": "0.9",
  "_foundIn": "Results",
  "_contextSnippet": "However, S462 cells did not activate STAT3 in response to IL-6 and had lower levels of total STAT3 in comparison to ST88-14 and NF90-8 cells",
  "resourceType": "Cell Line",
  "resourceName": "S462",
  "observationType": "Other",
  "details": "Did not activate STAT3 in response to IL-6 and had lower levels of total STAT3 compared to ST88-14 and NF90-8 cells",
  "referencePublication": "10.1038/s41416-021-01270-8"
}