{
  "_source": "mining",
  "_publications": [
    {
      "_pmid": "PMID:38203448",
      "_doi": "10.3390/ijms25010277",
      "_publicationTitle": "FT895 Impairs Mitochondrial Function in Malignant Peripheral Nerve Sheath Tumor Cells."
    }
  ],
  "_confidence": "0.9",
  "_foundIn": "Results",
  "_contextSnippet": "Further analysis to determine the mean fluorescent intensity revealed a significant increase in ROS levels in S462TY, STS26T, and T265 cells",
  "resourceType": "Cell Line",
  "resourceName": "STS26T",
  "observationType": "Molecular",
  "details": "Significant increase in ROS levels after 24h treatment with 10 μM FT895",
  "referencePublication": "10.3390/ijms25010277"
}