{
  "_source": "mining",
  "_publications": [
    {
      "_pmid": "PMID:41871910",
      "_doi": "10.1101/gad.353336.125",
      "_publicationTitle": "Nested pediatric low-grade glioma cerebral organoid avatars reveal glutamatergic neuron stromal growth dependency."
    }
  ],
  "_confidence": "0.95",
  "_foundIn": "Results",
  "_contextSnippet": "WUPA cells were strongly immunopositive for GFAP, a small portion (<10%) were faintly immunopositive for OLIG2, and were all negative for synaptophysin (neuronal marker)",
  "resourceType": "Cell Line",
  "resourceName": "WUPA cells",
  "observationType": "Other",
  "details": "Strongly immunopositive for GFAP, small portion (<10%) faintly immunopositive for OLIG2, and all negative for synaptophysin expression",
  "referencePublication": "10.1101/gad.353336.125"
}