{
  "_source": "mining",
  "_publications": [
    {
      "_pmid": "PMID:33413690",
      "_doi": "10.1186/s40478-020-01103-4",
      "_publicationTitle": "Human cutaneous neurofibroma matrisome revealed by single-cell RNA sequencing."
    }
  ],
  "_confidence": "0.7",
  "_foundIn": "Results",
  "_contextSnippet": "We analyzed each sample individually for quality control.",
  "resourceType": "Computational Tool",
  "resourceName": "Cell Ranger version 3.0.0",
  "observationType": "Other",
  "details": "Successfully processed single-cell RNA sequencing data from cutaneous neurofibroma samples",
  "referencePublication": "10.1186/s40478-020-01103-4"
}