{
  "_source": "mining",
  "_publications": [
    {
      "_pmid": "PMID:40025578",
      "_doi": "10.1186/s40478-025-01965-6",
      "_publicationTitle": "Development of CAR-T cell therapy for NF1/SWN-related nerve sheath tumor treatment."
    }
  ],
  "_confidence": "0.8",
  "_foundIn": "Results",
  "_contextSnippet": "The cytolytic effect was assessed using Real Time Cell Analysis (RTCA)",
  "resourceType": "Computational Tool",
  "resourceName": "iCELLigence (ACEA Biosciences)",
  "observationType": "Other",
  "details": "Successfully assessed cytolytic effects of CAR-T cells on primary tumor cells using Real Time Cell Analysis",
  "referencePublication": "10.1186/s40478-025-01965-6"
}