{
  "_source": "mining",
  "_publications": [
    {
      "_pmid": "PMID:32383545",
      "_doi": "10.15252/embr.201949117",
      "_publicationTitle": "Hexokinase 2 displacement from mitochondria-associated membranes prompts Ca"
    }
  ],
  "_confidence": "0.85",
  "_foundIn": "Results",
  "_contextSnippet": "Quantification of panel B experiment showing the percentage of HK2 dots that merge with MAMs in HeLa cells",
  "resourceType": "Computational Tool",
  "resourceName": "ImageJ",
  "observationType": "Other",
  "details": "Used for quantification of HK2 dots merging with MAMs and co-localization analysis",
  "referencePublication": "10.15252/embr.201949117"
}