{
  "_source": "mining",
  "_publications": [
    {
      "_pmid": "PMID:34010628",
      "_doi": "10.1016/j.stem.2021.04.029",
      "_publicationTitle": "Stem-like cells drive NF1-associated MPNST functional heterogeneity and tumor progression."
    }
  ],
  "_confidence": "0.85",
  "_foundIn": "Results",
  "_contextSnippet": "Stringent gating for GFP was applied to effectively segregate GFP+ and GFP- tumor populations and to reduce cross-contamination",
  "resourceType": "Computational Tool",
  "resourceName": "S3e sorter",
  "observationType": "Other",
  "details": "Enabled effective segregation of GFP+ and GFP- tumor populations with stringent gating to reduce cross-contamination for functional studies",
  "referencePublication": "10.1016/j.stem.2021.04.029"
}