{
  "_source": "mining",
  "_publications": [
    {
      "_pmid": "PMID:33025139",
      "_doi": "10.1007/s00401-020-02230-x",
      "_publicationTitle": "Epigenomic, genomic, and transcriptomic landscape of schwannomatosis."
    }
  ],
  "_confidence": "0.9",
  "_foundIn": "Results",
  "_contextSnippet": "demonstrating that SWNTS-SWNs (N = 18) partitioned mainly into one cluster, while NS-SWNs generated two separate clusters (Fig. 4a), suggesting that SWNs that arise in SWNTS patients harbor a distinct transcriptome profile",
  "resourceType": "Computational Tool",
  "resourceName": "STAR aligner",
  "observationType": "Other",
  "details": "Successfully processed RNA sequencing data that enabled identification of distinct transcriptome profiles, with SWNTS-SWNs partitioning mainly into one cluster while NS-SWNs generated two separate clusters",
  "referencePublication": "10.1007/s00401-020-02230-x"
}