{
  "basicInfo": {
    "ui:order": [
      "biobankName",
      "synonyms",
      "description",
      "biobankURL",
      "diseaseType",
      "specimenType",
      "specimenTissueType",
      "tumorType",
      "specimenPreparationMethod",
      "specimenFormat",
      "contact",
      "rrid",
      "developerName",
      "developerAffiliation"
    ],
    "description": { "ui:widget": "textarea" },
    "contact": { "ui:widget": "textarea" },
    "diseaseType": { "ui:widget": "checkboxes" },
    "specimenType": { "ui:widget": "checkboxes" },
    "specimenTissueType": { "ui:widget": "checkboxes" },
    "tumorType": { "ui:widget": "checkboxes" },
    "specimenPreparationMethod": { "ui:widget": "checkboxes" },
    "specimenFormat": { "ui:widget": "checkboxes" }
  },
  "itemAcquisition": { "ui:widget": "radio" },
  "usagePublicationDOIs": {
    "ui:options": { "addButtonText": "Add Another DOI", "itemTitle": "DOI", "orderable": false }
  },
  "resourceType": { "ui:widget": "hidden" }
}
