{
  "_source": "mining",
  "_publications": [
    {
      "_pmid": "PMID:37246765",
      "_doi": "10.1093/neuonc/noad097",
      "_publicationTitle": "Ex vivo to in vivo model of malignant peripheral nerve sheath tumors for precision oncology."
    }
  ],
  "_confidence": "0.9",
  "_foundIn": "Results",
  "_contextSnippet": "JH-2-079-c responded the least to all three drugs...exhibited a dramatic reduction in cell viability after five days in culture...combination therapy...significantly impeded tumor growth in vivo",
  "resourceType": "Patient-Derived Model",
  "resourceName": "JH-2-079-c",
  "observationType": "Other",
  "details": "Responded the least to all three drugs tested and exhibited dramatic reduction in cell viability after five days in culture with trabectedin plus olaparib or plus mirdametinib. Combination therapy with trabectedin plus olaparib (P < 0.05) and trabectedin plus mirdametinib (P < 0.05) significantly impeded tumor growth in vivo",
  "referencePublication": "10.1093/neuonc/noad097"
}