{
  "_source": "mining",
  "_publications": [
    {
      "_pmid": "PMID:40887659",
      "_doi": "10.1186/s40246-025-00803-z",
      "_publicationTitle": "RENOVO-NF1 accurately predicts NF1 missense variant pathogenicity."
    }
  ],
  "_confidence": "0.95",
  "_foundIn": "Results",
  "_contextSnippet": "As of July 2024, 13,460 NF1 variants are listed; most (5082, 37.7%) are classified as VUS",
  "resourceType": "biobank",
  "resourceName": "ClinVar",
  "observationType": "Other",
  "details": "Contains 13,460 NF1 variants as of July 2024, with 5082 (37.7%) classified as VUS and 5198 (38.6%) being missense variants",
  "referencePublication": "10.1186/s40246-025-00803-z"
}