{
  "_source": "mining",
  "_publications": [
    {
      "_pmid": "PMID:29787563",
      "_doi": "10.1371/journal.pone.0190001",
      "_publicationTitle": "Graph complexity analysis identifies an ETV5 tumor-specific network in human and murine low-grade glioma."
    }
  ],
  "_confidence": "0.9",
  "_foundIn": "Results",
  "_contextSnippet": "expression data from a normal control group (N, optic nerves from Nf1 flox/flox mice, which are equivalent to wild-type mice)",
  "resourceType": "Animal Model",
  "resourceName": "Nf1 flox/flox",
  "observationType": "Other",
  "details": "Used as normal control group (N) equivalent to wild-type mice for network complexity analysis",
  "referencePublication": "10.1371/journal.pone.0190001"
}