{
  "_source": "mining",
  "_publications": [
    {
      "_pmid": "PMID:34010628",
      "_doi": "10.1016/j.stem.2021.04.029",
      "_publicationTitle": "Stem-like cells drive NF1-associated MPNST functional heterogeneity and tumor progression."
    }
  ],
  "_confidence": "0.9",
  "_foundIn": "Results",
  "_contextSnippet": "Four DT doses (50 µg/kg) given on alternate days essentially eliminated CGD-expressing GFP+ cells without significantly altering the proportion of KI67+ cells",
  "resourceType": "Animal Model",
  "resourceName": "Nf1f/f;Trp53f/f;CGD",
  "observationType": "Other",
  "details": "Four DT doses (50 µg/kg) given on alternate days essentially eliminated CGD-expressing GFP+ cells",
  "referencePublication": "10.1016/j.stem.2021.04.029"
}