{
  "_source": "mining",
  "_publications": [
    {
      "_pmid": "PMID:27081657",
      "_doi": "10.1002/acn3.288",
      "_publicationTitle": "A randomized placebo-controlled lovastatin trial for neurobehavioral function in neurofibromatosis I."
    }
  ],
  "_confidence": "0.95",
  "_foundIn": "Results",
  "_contextSnippet": "There was also a differential effect in favor of statin treatment for verbal category fluency (P = 0.02; f² = 0.19)",
  "resourceType": "Clinical Assessment Tool",
  "resourceName": "Delis–Kaplan Executive Function Scale (D‐KEFS)",
  "observationType": "Other",
  "details": "Verbal category fluency showed significant differential treatment effect favoring lovastatin (P = 0.02, f² = 0.19), with scores improving from 9.83±3.06 to 10.43±2.15 in lovastatin group vs declining from 11.33±2.81 to 8.50±2.51 in placebo group",
  "referencePublication": "10.1002/acn3.288"
}