{
  "_source": "mining",
  "_publications": [
    {
      "_pmid": "PMID:38170419",
      "_doi": "10.1007/s11136-023-03574-z",
      "_publicationTitle": "Development of the PROMIS pediatric stigma and extension to the PROMIS pediatric stigma: skin item banks."
    }
  ],
  "_confidence": "0.88",
  "_foundIn": "Results",
  "_contextSnippet": "No items showed DIF between sample groups, indicating that the modified version, the PPS Measure...exhibited comparable measurement properties with the original version, the Neuro-QoL Pediatric Stigma Item bank",
  "resourceType": "Clinical Assessment Tool",
  "resourceName": "Neuro-QoL Pediatric Stigma Item Bank",
  "observationType": "Other",
  "details": "Exhibited comparable measurement properties with modified PPS version, showing no differential item functioning between sample groups",
  "referencePublication": "10.1007/s11136-023-03574-z"
}