{
  "_source": "mining",
  "_publications": [
    {
      "_pmid": "PMID:31033921",
      "_doi": "10.1097/MAO.0000000000002272",
      "_publicationTitle": "[18F]fluorothymidine and [18F]fluorodeoxyglucose PET Imaging Demonstrates Uptake and Differentiates Growth in Neurofibromatosis 2 Related Vestibular Schwannoma."
    }
  ],
  "_confidence": "0.92",
  "_foundIn": "Results",
  "_contextSnippet": "TrueV: adjusted R² value of 0.67 vs 0.73 with RM",
  "resourceType": "Clinical Assessment Tool",
  "resourceName": "Siemens Biograph TrueV PET-CT",
  "observationType": "Other",
  "details": "Achieved correlation between FDG and FLT SUV mean values with adjusted R² value of 0.67 without RM and 0.73 with RM",
  "referencePublication": "10.1097/MAO.0000000000002272"
}